pidet/__init__.py
pidet/cmd/__init__.py
pidet/cmd/pidet.py
pidet/fio/__init__.py
pidet/fio/parser.py
pidet/influxdb/__init__.py
pidet/influxdb/writer.py
pidet/iperf3/__init__.py
pidet/iperf3/parser.py
pidet-0.2.0.dist-info/AUTHORS
pidet-0.2.0.dist-info/LICENSE
pidet-0.2.0.dist-info/METADATA
pidet-0.2.0.dist-info/WHEEL
pidet-0.2.0.dist-info/entry_points.txt
pidet-0.2.0.dist-info/pbr.json
pidet-0.2.0.dist-info/top_level.txt
pidet-0.2.0.dist-info/RECORD
